Black_Pearl_Discord/__init__.py
Black_Pearl_Discord-0.1.dist-info/METADATA
Black_Pearl_Discord-0.1.dist-info/WHEEL
Black_Pearl_Discord-0.1.dist-info/top_level.txt
Black_Pearl_Discord-0.1.dist-info/RECORD
