Metadata-Version: 2.1
Name: Black-Pearl-Discord
Version: 0.1
Summary: Module for youtube
Author: Landry Ingouffre
Author-email: Landry.Ingouffredevelopper89@gmail.com
Classifier: Programming Language :: Python :: 3
Classifier: License :: OSI Approved :: MIT License
Classifier: Operating System :: OS Independent
